excelize.cpython-39-darwin.h
excelize.cpython-39-darwin.so
pyexcelize.py
setup.py
tests/__init__.py
tests/excelize_only.go
tests/perform_openpyxl.py
tests/template.xlsx
tests/test_pyexcelize.py
pyexcelize-0.2.4.dist-info/METADATA
pyexcelize-0.2.4.dist-info/WHEEL
pyexcelize-0.2.4.dist-info/top_level.txt
pyexcelize-0.2.4.dist-info/RECORD
