Metadata-Version: 2.1
Name: pyexcelize
Version: 0.2.4
Summary: A Python library for reading and writing Excel files
Home-page: UNKNOWN
Author: Junichi Yukawa
Author-email: j.yukawa@gmail.com
License: MIT
Platform: UNKNOWN
Requires-Python: >=3.7
Requires-Dist: Faker (==13.3.0)
Requires-Dist: setuptools-golang (==2.7.0)
